LICENSE.txt
MANIFEST.in
README.txt
setup.py
version.txt
lrdgdal/__init__.py
lrdgdal/gdalrdf.py
lrdgdal/gdalutils.py
lrdgdal/ogcutils.py
lrdgdal/sparql.py
lrdgdal/xml2rdf.xsl
lrdgdal.egg-info/PKG-INFO
lrdgdal.egg-info/SOURCES.txt
lrdgdal.egg-info/dependency_links.txt
lrdgdal.egg-info/requires.txt
lrdgdal.egg-info/top_level.txt
lrdgdal/classes/BandRDFGraph.py
lrdgdal/classes/Raster.py
lrdgdal/classes/RasterRDFDataset.py
lrdgdal/classes/__init__.py
lrdgdal/namespace/GDAL.py
lrdgdal/namespace/GEOSPARQL.py
lrdgdal/namespace/__init__.py