Metadata-Version: 1.0
Name: lrdgdal
Version: 0.0.5
Summary: Linked Raster Data for gdal for python
Home-page: http://scharrenbach.net
Author: Thomas Scharrenbach
Author-email: thomas@scharrenbach.net
License: Apache License v2
Platform: UNKNOWN
